LICENSE
MANIFEST.in
README.md
requirements.txt
setup.py
leihs_ldap_authenticator.egg-info/PKG-INFO
leihs_ldap_authenticator.egg-info/SOURCES.txt
leihs_ldap_authenticator.egg-info/dependency_links.txt
leihs_ldap_authenticator.egg-info/requires.txt
leihs_ldap_authenticator.egg-info/top_level.txt
leihsldap/__init__.py
leihsldap/__main__.py
leihsldap/authenticator.py
leihsldap/config.py
leihsldap/ldap.py
leihsldap/leihs_api.py
leihsldap/web.py
leihsldap/i18n/error-de.yml
leihsldap/i18n/error-en.yml
leihsldap/i18n/i18n-de.yml
leihsldap/i18n/i18n-en.yml
leihsldap/static/style.css
leihsldap/templates/error.html
leihsldap/templates/login.html