Metadata-Version: 2.1
Name: leihs-ldap-authenticator
Version: 0.5
Summary: UNKNOWN
Home-page: https://github.com/elan-ev/leihs-ldap-authenticator
Author: Lars Kiesow <kiesow@elan-ev.de>
License: GPLv3+
Platform: UNKNOWN
License-File: LICENSE
